README.rst
setup.py
tests/file_app/__init__.py
tests/file_app/models.py
tests/file_app/rest.py
tests/file_app/migrations/__init__.py
tests/swap_app/__init__.py
tests/swap_app/models.py
tests/swap_app/migrations/__init__.py
vera/__init__.py
vera/base_models.py
vera/models.py
vera.egg-info/PKG-INFO
vera.egg-info/SOURCES.txt
vera.egg-info/dependency_links.txt
vera.egg-info/requires.txt
vera.egg-info/top_level.txt
vera/params/__init__.py
vera/params/models.py
vera/params/rest.py
vera/params/wizard.py
vera/params/migrations/__init__.py
vera/results/__init__.py
vera/results/compat.py
vera/results/filters.py
vera/results/models.py
vera/results/rest.py
vera/results/serializers.py
vera/results/views.py
vera/results/migrations/__init__.py
vera/series/__init__.py
vera/series/models.py
vera/series/rest.py
vera/series/serializers.py
vera/series/wizard.py
vera/series/migrations/__init__.py