Metadata-Version: 1.1
Name: vera
Version: 1.0.0
Summary: Reference implementation of the ERAV data model for citizen science. ERAV is an extension to EAV with support for maintaining multi-faceted provenance metadata for an entity.
Home-page: https://wq.io/vera
Author: S. Andrew Sheppard
Author-email: andrew@wq.io
License: MIT
Platform: UNKNOWN
Classifier: Development Status :: 5 - Production/Stable
Classifier: Environment :: Web Environment
Classifier: License :: OSI Approved :: MIT License
Classifier: Natural Language :: English
Classifier: Programming Language :: JavaScript
Classifier: Programming Language :: Python :: 2
Classifier: Programming Language :: Python :: 2.7
Classifier: Programming Language :: Python :: 3
Classifier: Programming Language :: Python :: 3.4
Classifier: Programming Language :: Python :: 3.5
Classifier: Programming Language :: Python :: 3.6
Classifier: Framework :: Django
Classifier: Framework :: Django :: 1.8
Classifier: Framework :: Django :: 1.9
Classifier: Framework :: Django :: 1.10
Classifier: Framework :: Django :: 1.11
Classifier: Topic :: Scientific/Engineering :: GIS
Classifier: Topic :: Database :: Database Engines/Servers
